setup.py
jadelesscoffee/__init__.py
jadelesscoffee/wsgi/__init__.py
jadelesscoffee/wsgi/middleware.py
jadelesscoffee_middleware.egg-info/PKG-INFO
jadelesscoffee_middleware.egg-info/SOURCES.txt
jadelesscoffee_middleware.egg-info/dependency_links.txt
jadelesscoffee_middleware.egg-info/top_level.txt