Metadata-Version: 1.1
Name: jadelesscoffee-middleware
Version: 0.3.0
Summary: WSGI middleware class that executes the Node.js JadeLessCoffee compiler on a `src` folder in the JLC_DIRS environment variable.
Home-page: http://github.com/nuulogic/jadelesscoffee-middleware/
Author: Oliver Wilkerson, Matthew Wells, Jeff Andrews, Nuu Logic LLC
Author-email: oliver.wilkerson@nuulogic.com
License: UNKNOWN
Keywords: wsgi,jade,less,lesscss,coffeescript,nodejs,node,npm,coffee,jlc,middleware
Platform: UNKNOWN
Classifier: Development Status :: 4 - Beta
Classifier: Topic :: Internet :: WWW/HTTP :: WSGI :: Middleware
Classifier: Intended Audience :: Developers
Classifier: License :: OSI Approved :: GNU General Public License v3 or later (GPLv3+)
Classifier: Operating System :: OS Independent
Classifier: Programming Language :: Python
Classifier: Programming Language :: JavaScript
